YassaAlchemy/__init__.py
YassaAlchemy-0.0.1.dist-info/LICENCE.txt
YassaAlchemy-0.0.1.dist-info/METADATA
YassaAlchemy-0.0.1.dist-info/WHEEL
YassaAlchemy-0.0.1.dist-info/top_level.txt
YassaAlchemy-0.0.1.dist-info/RECORD
